{
  "NEWRESETFORGOT":"/reset-password-forgot/:uuid",
  "VERIFYEMAIL": "/verify-email-login",
  "ORAL": "/new/oral-health",
  "TREATMENTPLAN": "/new/treatment-plan",
  "NEWHOME": "/new/home",
  "PROCEDURES": "/data/procedures",
  "HEALTHCATEGORY": "/data/health-categories",
  "APPOINTMENTTYPE": "/office/appointments",
  "PROVIDER": "/provider/:id",
  "CLINICPROFILE": "/clinic/:id",
  "HOMEPAGE": "/Home/",
  "SEARCHRESULT": "/search-result/",
  "PLANMANAGEMENT": "/plans-management/",
  "SERVICEMANAGEMENT": "/services-management/",
  "FAILEDPAYMENTS": "/failed-payments/",
  "TRAMSACTIONS": "/transactions/",
  "CREATEOFFICE": "/create-office/",
  "ARDETAIL": "/ar-detail/:uuid",
  "SETREVIEW": "/set-review/:token",
  "AR": "/ar",
  "REVIEW": "/office/review",
  "PROFILE": "/office/profile",
  "OFFICES": "/offices",
  "FINANACE": "/finance-flow",
  "SUBSCRIPTIONS": "/Subscriptions/:uuid",
  "DISCOUNTOPTIONS": "/discount-options",
  "ACCOUNTSRECEIVABLE": "/payment-requests",
  "MEMBERS": "/members",
  "APPOINTMENTS": "/appointments",
  "PLANS": "/plans",
  "PLANDETAIL": "/plan-detail/:uuid",
  "ADDACCOUNT": "/add-connected-account",
  "PAYMENT": "/payment/:uuid",
  "PAYMENTDONE": "/payment-Done",
  "PAYMENTDONEMULTI": "/wizard-payment-Done",
  "HOME": "/home",
  "UPLOADPDF": "/upload-pdf",
  "LOGIN": "/",
  "LOGINNEW": "/new-login",
  "LOGINPAGE": "/login/:email",
  "LOGOUT": "/login/action/:action?",
  "PAYMENTREQUEST": "/paymentrequest",
  "DASHBOARD": "/dashboard",
  "PASSWORD": "/password",
  "CHECKOUT": "/checkout/:uuid",
  "ADD_PROVIDER": "/add-provider",
  "COUNTER": "/counter",
  "CONTACT": "/contact",
  "BOOKINGMAIN": "/booking",
  "BOOKINGSTEPONE": "/booking-step-one",
  "BOOKINGSTEPTWO": "/booking-step-two",
  "BOOKINGSTEPTHREE": "/booking-step-three",
  "PASSWORDMODE": "/password/:token",
  "REGISTRATION": "/booking-step-four",
  "BOOKINGSUMMARY": "/booking-summary",
  "DONEBOOKING": "/done",
  "RESETCONFIRM": "/password/reset",
  "PROVIDERSCHEDULING": "/provider-scheduling",
  "ERRORNOTFOUND": "/error404",
  "ERRORSERVER": "/error500",
  "PAYMENTWIZARD": "/wizard-payment/:uuid",
  "PAYMENTWIZARDSTEP2": "/wizard-payment-step-2/:uuid",
  "PAYMENTWIZARDSTEPDONE": "/wizard-payment-step-done",
  "SINGLEPAYMENT": "/single-payment/:id",
  "VISIT": "/visit",
  "PAYMENTFLOW": "/payment-flow/:id",
  "TreatmentPlans": "/treatment-plans",
  "Campaigns": "/campaigns",
  "CreateCampaigns": "/create-campaigns"
}
